cp1-alu/alu-main/or32.v
module or32(out, in1, in2);
    input [31:0] in1, in2;
    output [31:0] out;
    or n0(out[0], in1[0], in2[0]);
    or n1(out[1], in1[1], in2[1]);
    or n2(out[2], in1[2], in2[2]);
    or n3(out[3], in1[3], in2[3]);
    or n4(out[4], in1[4], in2[4]);
    or n5(out[5], in1[5], in2[5]);
    or n6(out[6], in1[6], in2[6]);
    or n7(out[7], in1[7], in2[7]);

    or n8(out[8], in1[8], in2[8]);
    or n9(out[9], in1[9], in2[9]);
    or n10(out[10], in1[10], in2[10]);
    or n11(out[11], in1[11], in2[11]);
    or n12(out[12], in1[12], in2[12]);
    or n13(out[13], in1[13], in2[13]);
    or n14(out[14], in1[14], in2[14]);
    or n15(out[15], in1[15], in2[15]);

    or n16(out[16], in1[16], in2[16]);
    or n17(out[17], in1[17], in2[17]);
    or n18(out[18], in1[18], in2[18]);
    or n19(out[19], in1[19], in2[19]);
    or n20(out[20], in1[20], in2[20]);
    or n21(out[21], in1[21], in2[21]);
    or n22(out[22], in1[22], in2[22]);
    or n23(out[23], in1[23], in2[23]);

    or n24(out[24], in1[24], in2[24]);
    or n25(out[25], in1[25], in2[25]);
    or n26(out[26], in1[26], in2[26]);
    or n27(out[27], in1[27], in2[27]);
    or n28(out[28], in1[28], in2[28]);
    or n29(out[29], in1[29], in2[29]);
    or n30(out[30], in1[30], in2[30]);
    or n31(out[31], in1[31], in2[31]);
endmodule

cp1-alu/ishan-files/tbs/or32_tb.v
`timescale 1 ns / 100 ps
module or32_tb;
    reg [31:0] in0, in1;
    wire [31:0] out, expected;

    // to do
    or32 or_gate(.out(out), .in1(in0), .in2(in1));
    assign expected = in0 | in1;

    initial begin
        in0 = 32'h00000000;
        in1 = 32'h00000000;
        #240;
        $finish;
    end
    always begin
        #10 in0 = $random;
        #10 in1 = $random;
    end
    always @(in0, in1) begin
        #1;
        if(expected === out) begin
            $display("PASSED: A:%b, B:%b => Out:%b", in0, in1, out);
        end else begin 
            $display("FAILED: A:%b, B:%b => Out:%b", in0, in1, out);
        end
    end    
    initial begin
        $dumpfile("or32_waveform.vcd");
        $dumpvars(0, or32_tb);
    end    

endmodule

cp1-alu/ishan-files/tbs/or32_waveform.vcd
$date
	Thu Sep 12 11:06:10 2024
$end
$version
	Icarus Verilog
$end
$timescale
	100ps
$end
$scope module or32_tb $end
$var wire 32 ! expected [31:0] $end
$var wire 32 " out [31:0] $end
$var reg 32 # in0 [31:0] $end
$var reg 32 $ in1 [31:0] $end
$scope module or_gate $end
$var wire 32 % in1 [31:0] $end
$var wire 32 & in2 [31:0] $end
$var wire 32 ' out [31:0] $end
$upscope $end
$upscope $end
$enddefinitions $end
#0
$dumpvars
b0 '
b0 &
b0 %
b0 $
b0 #
b0 "
b0 !
$end
#100
b10010000101010011010100100100 "
b10010000101010011010100100100 '
b10010000101010011010100100100 !
b10010000101010011010100100100 #
b10010000101010011010100100100 %
#200
b11010010100111010111111110100101 "
b11010010100111010111111110100101 '
b11010010100111010111111110100101 !
b11000000100010010101111010000001 $
b11000000100010010101111010000001 &
#300
b11000100100011011101111010001001 "
b11000100100011011101111010001001 '
b11000100100011011101111010001001 !
b10000100100001001101011000001001 #
b10000100100001001101011000001001 %
#400
b10110101111101001101011001101011 "
b10110101111101001101011001101011 '
b10110101111101001101011001101011 !
b10110001111100000101011001100011 $
b10110001111100000101011001100011 &
#500
b10110111111110010111111101101111 "
b10110111111110010111111101101111 '
b10110111111110010111111101101111 !
b110101110010111101100001101 #
b110101110010111101100001101 %
#600
b1000110111111111111101110001101 "
b1000110111111111111101110001101 '
b1000110111111111111101110001101 !
b1000110110111111001100110001101 $
b1000110110111111001100110001101 &
#700
b11110110110111111001110111101101 "
b11110110110111111001110111101101 '
b11110110110111111001110111101101 !
b10110010110000101000010001100101 #
b10110010110000101000010001100101 %
#800
b10111011111101111101011001110111 "
b10111011111101111101011001110111 '
b10111011111101111101011001110111 !
b10001001001101110101001000010010 $
b10001001001101110101001000010010 &
#900
b10001001111101111111001100010011 "
b10001001111101111111001100010011 '
b10001001111101111111001100010011 !
b111100111110001100000001 #
b111100111110001100000001 %
#1000
b110111101111110111100001101 "
b110111101111110111100001101 '
b110111101111110111100001101 !
b110110101111100110100001101 $
b110110101111100110100001101 &
#1100
b111111111101111111110101111111 "
b111111111101111111110101111111 '
b111111111101111111110101111111 !
b111011001000111111000101110110 #
b111011001000111111000101110110 %
#1200
b111111101011111111110101111111 "
b111111101011111111110101111111 '
b111111101011111111110101111111 !
b11110100011011100110100111101 $
b11110100011011100110100111101 &
#1300
b1111110110111011101111111111101 "
b1111110110111011101111111111101 '
b1111110110111011101111111111101 !
b1110110110101000101011111101101 #
b1110110110101000101011111101101 %
#1400
b1110110111111011111011111101101 "
b1110110111111011111011111101101 '
b1110110111111011111011111101101 !
b1000110001011011111011110001100 $
b1000110001011011111011110001100 &
#1500
b1111110111111011111111111111101 "
b1111110111111011111111111111101 '
b1111110111111011111111111111101 !
b1111100111111011110100111111001 #
b1111100111111011110100111111001 %
#1600
b11111111111111111110110111111111 "
b11111111111111111110110111111111 '
b11111111111111111110110111111111 !
b11100011001101110010010011000110 $
b11100011001101110010010011000110 &
#1700
b11100011111101111010010011000111 "
b11100011111101111010010011000111 '
b11100011111101111010010011000111 !
b11100010111101111000010011000101 #
b11100010111101111000010011000101 %
#1800
b11110111111101111101011011101111 "
b11110111111101111101011011101111 '
b11110111111101111101011011101111 !
b11010101000100111101001010101010 $
b11010101000100111101001010101010 &
#1900
b11110111101111111111011111101111 "
b11110111101111111111011111101111 '
b11110111101111111111011111101111 !
b1110010101011111111011111100101 #
b1110010101011111111011111100101 %
#2000
b11111011111111111111011111110111 "
b11111011111111111111011111110111 '
b11111011111111111111011111110111 !
b10111011110100100111001001110111 $
b10111011110100100111001001110111 &
#2100
b10111011111100101111011001110111 "
b10111011111100101111011001110111 '
b10111011111100101111011001110111 !
b10001001001100101101011000010010 #
b10001001001100101101011000010010 %
#2200
b11001111111111101101111110011111 "
b11001111111111101101111110011111 '
b11001111111111101101111110011111 !
b1000111111011001101101110001111 $
b1000111111011001101101110001111 &
#2300
b1111111111111001111101111111111 "
b1111111111111001111101111111111 '
b1111111111111001111101111111111 !
b1111001001100000110100111110010 #
b1111001001100000110100111110010 %
