cp1-alu/alu-main/sra.v
module sra(in, out, sh_amt);
    input [4:0] sh_amt;
    input [31:0] in;
    output [31:0] out;

    // intermediate wires
    wire [31:0] s1, s2, s4, s8, s16;
    wire [31:0] ta, tb, tc, td;
    wire [31:0] zero;
    
    // reverse order; starts with least significant bit
    assign s1 = {in[31],in[31:1]};
    assign ta = sh_amt[0] ? s1 : in;

    assign s2 = {{2{ta[31]}},ta[31:2]};
    assign tb = sh_amt[1] ? s2 : ta;

    assign s4 = {{4{tb[31]}},tb[31:4]};
    assign tc = sh_amt[2] ? s4 : tb;

    assign s8 = {{8{tc[31]}},tc[31:8]};
    assign td = sh_amt[3] ? s8 : tc;

    assign s16 = {{16{td[31]}},td[31:16]};
    assign out = sh_amt[4] ? s16 : td;    
endmodule

cp1-alu/ishan-files/tbs/sra_tb.v
`timescale 1 ns / 100 ps
module sra_tb();
    reg[31:0] in;
    reg[4:0] sh_amt;
    wire[31:0] out, expected, diff;
    sra sra(.in(in), .sh_amt(sh_amt), .out(out));

    assign expected = $signed(in) >>> sh_amt;
    assign diff = out - expected;

    initial begin
        in = 32'd0;
        sh_amt = 5'd0;
        #240;   
        $finish;
    end
    always 
        #10 in = $random;
    always 
        #10 sh_amt = $random;
    always @(in) begin
        #5;
        if(expected === out) begin
            $display("PASSED: In:%b, Shift:%b => Out:%b", in, sh_amt, out);
        end else begin 
            $display("FAILED: In:%b, Shift:%b => Out:%b", in, sh_amt, out);
        end
    end    
    initial begin
        $dumpfile("sra_waveform.vcd");
        $dumpvars(0, sra_tb);
    end   

endmodule

cp1-alu/ishan-files/tbs/sra_waveform.vcd
$date
	Thu Sep 12 14:15:38 2024
$end
$version
	Icarus Verilog
$end
$timescale
	100ps
$end
$scope module sra_tb $end
$var wire 32 ! out [31:0] $end
$var wire 32 " expected [31:0] $end
$var wire 32 # diff [31:0] $end
$var reg 32 $ in [31:0] $end
$var reg 5 % sh_amt [4:0] $end
$scope module sra $end
$var wire 32 & in [31:0] $end
$var wire 5 ' sh_amt [4:0] $end
$var wire 32 ( td [31:0] $end
$var wire 32 ) tc [31:0] $end
$var wire 32 * tb [31:0] $end
$var wire 32 + ta [31:0] $end
$var wire 32 , s8 [31:0] $end
$var wire 32 - s4 [31:0] $end
$var wire 32 . s2 [31:0] $end
$var wire 32 / s16 [31:0] $end
$var wire 32 0 s1 [31:0] $end
$var wire 32 1 out [31:0] $end
$upscope $end
$upscope $end
$enddefinitions $end
#0
$dumpvars
b0 1
b0 0
b0 /
b0 .
b0 -
b0 ,
b0 +
b0 *
b0 )
b0 (
b0 '
b0 &
b0 %
b0 $
b0 #
b0 "
b0 !
$end
#100
b100100001010 /
b1001000010101001101010010010 !
b1001000010101001101010010010 1
b10010000101010011010 ,
b1001000010101001101010010010 (
b100100001010100110101001 -
b1001000010101001101010010010 )
b10010000101010011010100100 .
b1001000010101001101010010010 *
b1001000010101001101010010010 0
b1001000010101001101010010010 +
b1 %
b1 '
b0 #
b1001000010101001101010010010 "
b10010000101010011010100100100 $
b10010000101010011010100100100 &
#200
b11111111111111111111000010010000 /
b11110000100100001001101011000001 !
b11110000100100001001101011000001 1
b11111111111100001001000010011010 ,
b11110000100100001001101011000001 (
b11111111000010010000100110101100 -
b11110000100100001001101011000001 )
b11110000100100001001101011000001 .
b11110000100100001001101011000001 *
b11000010010000100110101100000100 +
b11000010010000100110101100000100 0
b11 %
b11 '
b0 #
b11110000100100001001101011000001 "
b10000100100001001101011000001001 $
b10000100100001001101011000001001 &
#300
b1101011100101111011000 -
b11010111001011 ,
b0 /
b11010111001011 !
b11010111001011 1
b110101110010111101100001 .
b11010111001011110110000110 *
b1101011100101111011000 )
b11010111001011 (
b11010111001011110110000110 +
b11010111001011110110000110 0
b1101 %
b1101 '
b0 #
b11010111001011 "
b110101110010111101100001101 $
b110101110010111101100001101 &
#400
b11111110110010110000101000010001 -
b11111111111011001011000010100001 ,
b11111111111111111110110010110000 /
b11101100101100001010000100011001 .
b11101100101100001010000100011001 *
b11101100101100001010000100011001 )
b11101100101100001010000100011001 (
b11111111111111111110110010110000 !
b11111111111111111110110010110000 1
b10110010110000101000010001100101 +
b11011001011000010100001000110010 0
b10010 %
b10010 '
b0 #
b11111111111111111110110010110000 "
b10110010110000101000010001100101 $
b10110010110000101000010001100101 &
#500
b1111001111100011000 -
b11110011111 ,
b0 /
b11110011111000110000000 *
b1111001111100011000 )
b11110011111 (
b11110011111 !
b11110011111 1
b111100111110001100000 .
b11110011111000110000000 0
b11110011111000110000000 +
b1101 %
b1101 '
b0 #
b11110011111 "
b111100111110001100000001 $
b111100111110001100000001 &
#600
b1 /
b11101100100011111 (
b11101100100011111 ,
b1110110010001111110001011 )
b1110110010001111110001011 -
b111011001000111111000101110 .
b11101100100011111100010111011 *
b1 !
b1 1
b11101100100011111100010111011 +
b11101100100011111100010111011 0
b11101 %
b11101 '
b0 #
b1 "
b111011001000111111000101110110 $
b111011001000111111000101110110 &
#700
b111 /
b1110110110101000101 (
b1110110110101000101 ,
b111011011010100010101111110 )
b111011011010100010101111110 -
b11101101101010001010111111011 .
b1110110110101000101011111101101 *
b1110110110101000101 !
b1110110110101000101 1
b1110110110101000101011111101101 +
b111011011010100010101111110110 0
b1100 %
b1100 '
b0 #
b1110110110101000101 "
b1110110110101000101011111101101 $
b1110110110101000101011111101101 &
#800
b11111001111110111 ,
b1111100111111011110100111 )
b111110011 /
b1111100111111011110100111 !
b1111100111111011110100111 1
b1111100111111011110100111 -
b1111100111111011110100111 (
b11111001111110111101001111110 .
b11111001111110111101001111110 *
b111110011111101111010011111100 0
b1111100111111011110100111111001 +
b110 %
b110 '
b0 #
b1111100111111011110100111 "
b1111100111111011110100111111001 $
b1111100111111011110100111111001 &
#900
b11111111100010111101111000010011 -
b11111111111110001011110111100001 ,
b11111111111111111111111111111000 /
b11111111111110001011110111100001 !
b11111111111110001011110111100001 1
b11111000101111011110000100110001 *
b11111000101111011110000100110001 )
b11111111111110001011110111100001 (
b11111000101111011110000100110001 .
b11110001011110111100001001100010 0
b11100010111101111000010011000101 +
b1010 %
b1010 '
b0 #
b11111111111110001011110111100001 "
b11100010111101111000010011000101 $
b11100010111101111000010011000101 &
#1000
b111001010101111111101111 -
b1110010101011111 ,
b11100101 /
b1110010101011111111011111100 *
b111001010101111111101111 )
b111001010101111111101111 (
b11100101 !
b11100101 1
b1110010101011111111011111100 .
b111001010101111111101111110010 0
b111001010101111111101111110010 +
b10111 %
b10111 '
b0 #
b11100101 "
b1110010101011111111011111100101 $
b1110010101011111111011111100101 &
#1100
b11111111111111110001001001100101 ,
b11111111000100100110010110101100 )
b11111111000100100110010110101100 -
b11110001001001100101101011000010 *
b11111111111111111111111111111111 /
b11110001001001100101101011000010 .
b11111111111111110001001001100101 (
b11111111111111110001001001100101 !
b11111111111111110001001001100101 1
b11000100100110010110101100001001 +
b11000100100110010110101100001001 0
b1111 %
b1111 '
b0 #
b11111111111111110001001001100101 "
b10001001001100101101011000010010 $
b10001001001100101101011000010010 &
#1200
b1 /
b11110010011000001 !
b11110010011000001 1
b11110010011000001 (
b11110010011000001 ,
b1111001001100000110100111 )
b1111001001100000110100111 -
b11110010011000001101001111100 *
b11110010011000001101001111100 .
b1111001001100000110100111110010 +
b111100100110000011010011111001 0
b1110 %
b1110 '
b0 #
b11110010011000001 "
b1111001001100000110100111110010 $
b1111001001100000110100111110010 &
#1300
b11111111111111111010000000000011 ,
b11111111101000000000001111010111 )
b11111111101000000000001111010111 -
b11111111111111111111111110100000 /
b11111111101000000000001111010111 !
b11111111101000000000001111010111 1
b11111010000000000011110101110100 *
b11111111101000000000001111010111 (
b11111110100000000000111101011101 .
b11111010000000000011110101110100 0
b11111010000000000011110101110100 +
b101 %
b101 '
b0 #
b11111111101000000000001111010111 "
b11110100000000000111101011101000 $
b11110100000000000111101011101000 &
#1400
b10111001011000010 ,
b1011100101100001001001010 )
b1011100101100001001001010 -
b1 /
b101110010110000100100101011 .
b10111001011000010010010101110 *
b10111001011000010 (
b1 !
b1 1
b10111001011000010010010101110 +
b10111001011000010010010101110 0
b11101 %
b11101 '
b0 #
b1 "
b101110010110000100100101011100 $
b101110010110000100100101011100 &
#1500
b11111111111111001011010101011010 ,
b11111100101101010101101011000001 )
b11111100101101010101101011000001 -
b11111111111111111111110010110101 /
b11110010110101010110101100000101 .
b11001011010101011010110000010110 *
b11111100101101010101101011000001 (
b11111100101101010101101011000001 !
b11111100101101010101101011000001 1
b11001011010101011010110000010110 +
b11001011010101011010110000010110 0
b101 %
b101 '
b0 #
b11111100101101010101101011000001 "
b10010110101010110101100000101101 $
b10010110101010110101100000101101 &
#1600
b11111110110001111011110110001001 -
b11111111111011000111101111011000 ,
b11111111111111111111111111101100 /
b11111111111011000111101111011000 !
b11111111111011000111101111011000 1
b11101100011110111101100010011000 .
b11101100011110111101100010011000 *
b11101100011110111101100010011000 )
b11111111111011000111101111011000 (
b10110001111011110110001001100011 +
b11011000111101111011000100110001 0
b1010 %
b1010 '
b0 #
b11111111111011000111101111011000 "
b10110001111011110110001001100011 $
b10110001111011110110001001100011 &
#1700
b11111111110000000011101100100010 ,
b11111100000000111011001000101000 -
b11000000001110110010001010000000 )
b11111111111111111100000000111011 /
b11000000001110110010001010000000 !
b11000000001110110010001010000000 1
b11000000001110110010001010000000 *
b11000000001110110010001010000000 (
b11110000000011101100100010100000 .
b11100000000111011001000101000000 0
b11000000001110110010001010000000 +
b0 %
b0 '
b0 #
b11000000001110110010001010000000 "
b11000000001110110010001010000000 $
b11000000001110110010001010000000 &
#1800
b101010101111000010 ,
b10 /
b10101010111100001000101101 -
b10101010111100001000101101 )
b101010101111000010 (
b10 !
b10 1
b1010101011110000100010110101 .
b101010101111000010001011010101 *
b101010101111000010001011010101 0
b101010101111000010001011010101 +
b11101 %
b11101 '
b0 #
b10 "
b1010101011110000100010110101010 $
b1010101011110000100010110101010 &
#1900
b11111111111111111111100101100100 !
b11111111111111111111100101100100 1
b11111111100101100100000001111101 -
b11111111111110010110010000000111 ,
b11111111111111111111100101100100 /
b11111001011001000000011111010010 .
b11111001011001000000011111010010 *
b11111001011001000000011111010010 )
b11111001011001000000011111010010 (
b11100101100100000001111101001011 +
b11100101100100000001111101001011 0
b10011 %
b10011 '
b0 #
b11111111111111111111100101100100 "
b11001011001000000011111010010110 $
b11001011001000000011111010010110 &
#2000
b11111111111111111111000011010111 !
b11111111111111111111000011010111 1
b11111111111111111111000011010111 /
b11111111111100001101011110000111 ,
b11110000110101111000011100000001 (
b11111111000011010111100001110000 -
b11110000110101111000011100000001 )
b11110000110101111000011100000001 *
b11110000110101111000011100000001 .
b11000011010111100001110000000110 +
b11000011010111100001110000000110 0
b0 #
b11111111111111111111000011010111 "
b10000110101111000011100000001101 $
b10000110101111000011100000001101 &
#2100
b110101100 !
b110101100 1
b110101100 /
b1101011001111111011101011 -
b11010110011111110 ,
b1101011001111111011101011 (
b110101100111111101110101101 .
b11010110011111110111010110101 *
b1101011001111111011101011 )
b11010110011111110111010110101 +
b11010110011111110111010110101 0
b10101 %
b10101 '
b0 #
b110101100 "
b110101100111111101110101101011 $
b110101100111111101110101101011 &
#2200
b11111111111111100000010001011101 ,
b11111110000001000101110100101000 )
b11111110000001000101110100101000 -
b11111111111111111111111111111110 /
b11100000010001011101001010000000 .
b11100000010001011101001010000000 *
b11111111111111100000010001011101 (
b11111111111111100000010001011101 !
b11111111111111100000010001011101 1
b10000001000101110100101000000010 +
b11000000100010111010010100000001 0
b1110 %
b1110 '
b0 #
b11111111111111100000010001011101 "
b10000001000101110100101000000010 $
b10000001000101110100101000000010 &
#2300
b0 /
b1110111111111 !
b1110111111111 1
b1110111111111 (
b1110111111111 ,
b111011111111111010010 )
b111011111111111010010 -
b1110111111111110100100011 *
b1110111111111110100100011 .
b111011111111111010010001110 0
b111011111111111010010001110 +
b1111 %
b1111 '
b0 #
b1110111111111 "
b1110111111111110100100011101 $
b1110111111111110100100011101 &
